demo/gradio_demo.py
demo/inference_from_file.py
vibevoice/__init__.py
vibevoice/modular/__init__.py
vibevoice/modular/configuration_vibevoice.py
vibevoice/modular/modeling_vibevoice.py
vibevoice/modular/modeling_vibevoice_inference.py
vibevoice/modular/modular_vibevoice_diffusion_head.py
vibevoice/modular/modular_vibevoice_text_tokenizer.py
vibevoice/modular/modular_vibevoice_tokenizer.py
vibevoice/modular/streamer.py
vibevoice/processor/__init__.py
vibevoice/processor/vibevoice_processor.py
vibevoice/processor/vibevoice_tokenizer_processor.py
vibevoice/schedule/__init__.py
vibevoice/schedule/dpm_solver.py
vibevoice/schedule/timestep_sampler.py
vibevoice/scripts/__init__.py
vibevoice/scripts/convert_nnscaler_checkpoint_to_transformers.py
vibevoice-0.0.1.dist-info/licenses/LICENSE
vibevoice-0.0.1.dist-info/METADATA
vibevoice-0.0.1.dist-info/WHEEL
vibevoice-0.0.1.dist-info/top_level.txt
vibevoice-0.0.1.dist-info/RECORD
